odoo10_addon_partner_bank_active-10.0.1.0.0-py2.7-nspkg.pth
odoo/addons/partner_bank_active/README.rst
odoo/addons/partner_bank_active/__init__.py
odoo/addons/partner_bank_active/__manifest__.py
odoo/addons/partner_bank_active/models/__init__.py
odoo/addons/partner_bank_active/models/res_partner_bank.py
odoo/addons/partner_bank_active/static/description/icon.png
odoo/addons/partner_bank_active/views/res_partner_bank.xml
odoo10_addon_partner_bank_active-10.0.1.0.0.dist-info/DESCRIPTION.rst
odoo10_addon_partner_bank_active-10.0.1.0.0.dist-info/METADATA
odoo10_addon_partner_bank_active-10.0.1.0.0.dist-info/RECORD
odoo10_addon_partner_bank_active-10.0.1.0.0.dist-info/WHEEL
odoo10_addon_partner_bank_active-10.0.1.0.0.dist-info/metadata.json
odoo10_addon_partner_bank_active-10.0.1.0.0.dist-info/namespace_packages.txt
odoo10_addon_partner_bank_active-10.0.1.0.0.dist-info/top_level.txt
